RapidHost/__init__.py
RapidHost-4.0.2.dist-info/METADATA
RapidHost-4.0.2.dist-info/WHEEL
RapidHost-4.0.2.dist-info/top_level.txt
RapidHost-4.0.2.dist-info/RECORD
